{"station": [{"orgDisplayName": {"$text": "WNYC Radio"}, "group": {"$text": "WNYC Radio", "id": "554"}, "name": {"$text": "WNYC-FM"}, "identifierAudioUrl": {"$text": "http://media.npr.org/stationid/554.mp4", "type": "mp4"}, "url": [{"typeId": "1", "$text": "http://www.wnyc.org/", "type": "Organization Home Page", "title": "WNYC-FM Homepage"}, {"typeId": "2", "$text": "http://www.wnyc.org/schedule/", "type": "Program Schedule", "title": "Program Schedule"}, {"typeId": "4", "$text": "https://pledge3.wnyc.org/epledge/?utm_source=npr&utm_medium=link&utm_campaign=pledge&utm_content=wnyc", "type": "Pledge Page", "title": "Support WNYC"}, {"typeId": "7", "$text": "http://www.wnyc.org/", "type": "Audio Stream Landing Page", "title": "WNYC-FM 93.9"}, {"typeId": "7", "$text": "http://www.wnyc.org", "type": "Audio Stream Landing Page", "title": "WNYC-AM 820"}, {"typeId": "9", "$text": "http://feeds.wnyc.org/wnyc_soundcheck", "type": "Podcast", "title": "Soundcheck"}, {"typeId": "9", "$text": "http://feeds.wnyc.org/onthemedia", "type": "Podcast", "title": "On The Media from WNYC and NPR"}, {"typeId": "9", "$text": "http://feeds.wnyc.org/wnyc_bl", "type": "Podcast", "title": "The Brian Lehrer Show"}, {"typeId": "9", "$text": "http://feeds.wnyc.org/fishko", "type": "Podcast", "title": "Fishko Files"}, {"typeId": "9", "$text": "http://feeds.wnyc.org/radiolab", "type": "Podcast", "title": "Radiolab"}, {"typeId": "9", "$text": "http://feeds.wnyc.org/studio360/podcast", "type": "Podcast", "title": "Studio 360"}, {"typeId": "9", "$text": "http://feeds.wnyc.org/wnyc_lopate", "type": "Podcast", "title": "The Leonard Lopate Show"}, {"typeId": "9", "$text": "http://www.wnyc.org/feeds/series/lopate/underreported", "type": "Podcast", "title": "Underreported from The Leonard Lopate Show"}, {"typeId": "9", "$text": "http://feeds.wnyc.org/radiorookies", "type": "Podcast", "title": "Radio Rookies"}, {"typeId": "9", "$text": "http://feeds.wnyc.org/wnyc/news/local/rss", "type": "Podcast", "title": "News from WNYC New York Public Radio"}, {"typeId": "9", "$text": "http://feeds.wnyc.org/wnyc/newsounds", "type": "Podcast", "title": "New Sounds"}, {"typeId": "9", "$text": "http://feeds.wnyc.org/lastchancefoods", "type": "Podcast", "title": "Last Chance Foods"}, {"typeId": "9", "$text": "http://feeds.wnyc.org/talk_to_me", "type": "Podcast", "title": "Talk To Me"}, {"typeId": "9", "$text": "http://feeds.wnyc.org/wnycheresthething/", "type": "Podcast", "title": "Here's The Thing"}, {"typeId": "9", "$text": "http://feeds.wnyc.org/itsafreecountrypodcast", "type": "Podcast", "title": "It's A Free Country: The Podcast"}, {"typeId": "9", "$text": "http://feeds.feedburner.com/freakonomicsradio", "type": "Podcast", "title": "Freakonomics Radio"}, {"typeId": "9", "$text": "http://feeds.wnyc.org/money-talking", "type": "Podcast", "title": "Money Talking"}, {"typeId": "9", "$text": "http://feeds.wnyc.org/new-tech-city", "type": "Podcast", "title": "New Tech City"}, {"typeId": "9", "$text": "http://www.npr.org/templates/rss/podcast.php?id=510018", "type": "Podcast", "title": "WNYC's Leonard Lopate Show: Please Explain"}, {"typeId": "10", "title": "WNYC-AM 820", "$text": "http://www.wnyc.org/stream/wnyc-am820/mp3.pls", "primary": "false", "guid": "4fcf71501b73444aa87f4dddb8165a39", "type": "Audio MP3 Stream"}, {"typeId": "10", "title": "WNYC-FM 93.9", "$text": "http://www.wnyc.org/stream/wnyc-fm939/mp3.pls", "primary": "true", "guid": "4fcf71501fed40a38998ea7960473a4a", "type": "Audio MP3 Stream"}, {"typeId": "13", "title": "WNYC-AM 820", "$text": "http://www.wnyc.org/stream/wnyc-am820/aac.pls", "primary": "false", "guid": "4fcf71501b73444aa87f4dddb8165a39", "type": "Audio AAC Stream"}, {"typeId": "13", "title": "WNYC-FM 93.9", "$text": "http://www.wnyc.org/stream/wnyc-fm939/aac.pls", "primary": "true", "guid": "4fcf71501fed40a38998ea7960473a4a", "type": "Audio AAC Stream"}, {"typeId": "15", "$text": "http://audio.wnyc.org/news/news_latest_newscast.mp3", "type": "Newscast", "title": "WNYC Newscast"}, {"typeId": "16", "$text": "http://www.facebook.com/WNYC", "type": "Facebook Url", "title": "Facebook"}, {"typeId": "17", "$text": "http://twitter.com/wnyc", "type": "Twitter Feed", "title": "Twitter"}], "tagline": [{"$text": "New York Public Radio"}], "signal": {"strength": "3", "$text": "moderate"}, "memberStatus": {"$text": "Member"}, "band": {"$text": "FM"}, "state": {"$text": "NY"}, "frequency": {"$text": "93.9"}, "orgId": {"$text": "554"}, "image": [{"$text": "http://media.npr.org/images/stations/logos/wnyc_fm.gif", "type": "logo"}], "marketCity": {"$text": "New York"}, "callLetters": {"$text": "WNYC"}, "coverage_url": {"$text": "/stations/station_xml/wnyc-fm_93.9.xml"}, "guid": {"$text": "4fcf70111c6a4fe4a3a1003825bf39b6"}, "id": "554", "network": {"$text": "WNYC Radio", "orgId": "552"}}, {"orgDisplayName": {"$text": "WWFM The Classical Network"}, "group": {"$text": "WWFM The Classical Network", "id": "918"}, "name": {"$text": "WWFM-FM"}, "identifierAudioUrl": {"$text": "http://media.npr.org/stationid/918.mp4", "type": "mp4"}, "url": [{"typeId": "1", "$text": "http://www.wwfm.org/", "type": "Organization Home Page", "title": "WWFM Homepage"}, {"typeId": "2", "$text": "http://www.publicbroadcasting.net/wwfm/guide.guidemain", "type": "Program Schedule", "title": "Program Schedule"}, {"typeId": "4", "$text": "https://secure.publicbroadcasting.net/wwfm/form.pledgemain?action=pledge&pg=pledgeForm", "type": "Pledge Page", "title": "Support"}, {"typeId": "7", "$text": "http://www.wwfm.org/listen.shtml", "type": "Audio Stream Landing Page", "title": "WWFM Classical"}, {"typeId": "7", "$text": "http://www.jazzon2.org", "type": "Audio Stream Landing Page", "title": "WWFM Jazz"}, {"typeId": "10", "title": "WWFM Classical", "$text": "http://ice8.securenetsystems.net/WWFM.m3u", "primary": "true", "guid": "4fcf716a095d4478b136bea0b2f2fb91", "type": "Audio MP3 Stream"}, {"typeId": "10", "title": "WWFM Jazz", "$text": "http://ice8.securenetsystems.net/JAZZON2.m3u", "primary": "false", "guid": "4fcf716a0f3e4398bfab50a0246ace42", "type": "Audio MP3 Stream"}, {"typeId": "16", "$text": "http://www.facebook.com/pages/WWFM-The-Classical-Network/93029131926", "type": "Facebook Url", "title": "Facebook"}, {"typeId": "17", "$text": "https://twitter.com/WWFMClassical", "type": "Twitter Feed", "title": "Twitter"}], "tagline": [{"$text": "WWFM The Classical Network"}], "signal": {"strength": "3", "$text": "moderate"}, "memberStatus": {"$text": "Member"}, "band": {"$text": "FM"}, "state": {"$text": "NJ"}, "frequency": {"$text": "89.1"}, "orgId": {"$text": "918"}, "image": [{"$text": "http://media.npr.org/images/stations/logos/wwfm_fm.gif", "type": "logo"}], "marketCity": {"$text": "Trenton"}, "callLetters": {"$text": "WWFM"}, "coverage_url": {"$text": "/stations/station_xml/wwfm-fm_89.1.xml"}, "guid": {"$text": "4fcf70131c104d059471122f69ae608c"}, "id": "918"}, {"orgDisplayName": {"$text": "New Jersey Public Radio"}, "name": {"$text": "WNJT-FM"}, "url": [{"typeId": "1", "$text": "http://www.njpublicradio.org/", "type": "Organization Home Page", "title": "New Jersey Public Radio Homepage"}, {"typeId": "2", "$text": "http://www.njpublicradio.org/", "type": "Program Schedule", "title": "Program Schedule"}, {"typeId": "4", "$text": "https://pledge3.wnyc.org/epledge/desktop/njpr/?utm_source=npr&utm_medium=splash&utm_campaign=pledge&utm_content=njpr", "type": "Pledge Page", "title": "Support NJPR"}, {"typeId": "7", "$text": "http://www.njpublicradio.org/", "type": "Audio Stream Landing Page", "title": "NJPR"}, {"typeId": "10", "title": "NJPR", "$text": "http://wnyc-nj.streamguys.com/njprweb.m3u", "primary": "true", "guid": "4fcf715013c04799af5adece6a5e6404", "type": "Audio MP3 Stream"}], "tagline": [{}], "signal": {"strength": "3", "$text": "moderate"}, "memberStatus": {"$text": "Member"}, "band": {"$text": "FM"}, "state": {"$text": "NJ"}, "frequency": {"$text": "88.1"}, "orgId": {"$text": "1243"}, "image": [{"$text": "http://media.npr.org/images/stations/logos/wnjt_fm.gif", "type": "logo"}], "marketCity": {"$text": "Trenton"}, "callLetters": {"$text": "WNJT"}, "coverage_url": {"$text": "/stations/station_xml/wnjt-fm_88.1.xml"}, "guid": {"$text": "4fcf7015057940baaa1da2ab65bb6f21"}, "id": "1243", "network": {"$text": "WNYC Radio", "orgId": "552"}}, {"orgDisplayName": {"$text": "WHYY"}, "group": {"$text": "WHYY-FM", "id": "433"}, "name": {"$text": "WHYY-FM"}, "identifierAudioUrl": {"$text": "http://media.npr.org/stationid/433.mp4", "type": "mp4"}, "url": [{"typeId": "1", "$text": "http://www.whyy.org/91FM/index.php", "type": "Organization Home Page", "title": "WHYY-FM Homepage"}, {"typeId": "2", "$text": "http://www.whyy.org/91FM/schedule.php", "type": "Program Schedule", "title": "Program Schedule"}, {"typeId": "4", "$text": "http://www.whyy.org/support/", "type": "Pledge Page", "title": "Support WHYY"}, {"typeId": "7", "$text": "http://www.whyy.org/91FM/live.php", "type": "Audio Stream Landing Page", "title": "WHYY-FM Listen Live"}, {"typeId": "7", "$text": "http://www.whyy.org/91FM/live.php", "type": "Audio Stream Landing Page", "title": "WHYY - Second Audio Program"}, {"typeId": "9", "$text": "http://www.whyy.org/rss/voices.xml", "type": "Podcast", "title": "WHYY's Voices in the Family"}, {"typeId": "9", "$text": "http://www.whyy.org/rss/garden.xml", "type": "Podcast", "title": "You Bet Your Garden"}, {"typeId": "9", "$text": "http://feeds.feedburner.com/NewsWorksTonight", "type": "Podcast", "title": "NewsWorks Tonight"}, {"typeId": "9", "$text": "http://www.whyy.org/rss/skytalk.xml", "type": "Podcast", "title": "Skytalk"}, {"typeId": "9", "$text": "http://www.npr.org/templates/rss/podcast.php?id=510027", "type": "Podcast", "title": "WHYY-FM: Radio Times Podcast"}, {"typeId": "10", "title": "WHYY - Second Audio Program", "$text": "http://207.245.67.206/listen.pls", "primary": "false", "guid": "4fcf7169163947a3a99a9cd9770cc6d7", "type": "Audio MP3 Stream"}, {"typeId": "10", "title": "WHYY-FM Listen Live", "$text": "http://207.245.67.209/91FM.m3u", "primary": "true", "guid": "4fcf713517374aeea549cae46ed92e27", "type": "Audio MP3 Stream"}, {"typeId": "11", "title": "WHYY-FM Listen Live", "$text": "http://www.whyy.org/91FM/whyy.asx", "primary": "true", "guid": "4fcf713517374aeea549cae46ed92e27", "type": "Audio Windows Media Stream"}, {"typeId": "12", "$text": "http://www.whyy.org/91FM/live40.ram", "type": "Audio Real Media Stream", "title": "WHYY-FM Listen Live"}, {"typeId": "15", "$text": "http://www.whyy.org/podcast/whyy_newscast.mp3", "type": "Newscast", "title": "WHYY-FM News"}, {"typeId": "16", "$text": "http://www.facebook.com/whyypublicmedia", "type": "Facebook Url", "title": "Facebook"}, {"typeId": "17", "$text": "http://www.twitter.com/whyy", "type": "Twitter Feed", "title": "Twitter"}], "tagline": [{"$text": "Public Media Serving Southeastern Pennsylvania, Delaware, South Jersey and the world"}], "signal": {"strength": "1", "$text": "weak"}, "memberStatus": {"$text": "Member"}, "band": {"$text": "FM"}, "state": {"$text": "PA"}, "frequency": {"$text": "90.9"}, "orgId": {"$text": "433"}, "image": [{"$text": "http://media.npr.org/images/stations/logos/whyy_fm.gif", "type": "logo"}], "marketCity": {"$text": "Philadelphia"}, "callLetters": {"$text": "WHYY"}, "coverage_url": {"$text": "/stations/station_xml/whyy-fm_90.9.xml"}, "guid": {"$text": "4fcf701025bc43a0b6fd7dd8d6dcd418"}, "id": "433", "network": {"$text": "WHYY, Inc.", "orgId": "432"}}, {"orgDisplayName": {"$text": "WNYC Radio"}, "group": {"$text": "WNYC Radio", "id": "554"}, "name": {"$text": "WNYC-AM"}, "identifierAudioUrl": {"$text": "http://media.npr.org/stationid/553.mp4", "type": "mp4"}, "url": [{"typeId": "1", "$text": "http://www.wnyc.org/", "type": "Organization Home Page", "title": "WNYC-AM Homepage"}, {"typeId": "2", "$text": "http://www.wnyc.org/schedule/", "type": "Program Schedule", "title": "Program Schedule"}, {"typeId": "4", "$text": "https://pledge3.wnyc.org/epledge/?utm_source=npr&utm_medium=link&utm_campaign=pledge&utm_content=wnyc", "type": "Pledge Page", "title": "Support WNYC"}, {"typeId": "7", "$text": "http://www.wnyc.org/", "type": "Audio Stream Landing Page", "title": "WNYC-AM 820"}, {"typeId": "7", "$text": "http://www.wnyc.org/", "type": "Audio Stream Landing Page", "title": "WNYC-FM 93.9"}, {"typeId": "9", "$text": "http://feeds.wnyc.org/radiolab", "type": "Podcast", "title": "Radiolab"}, {"typeId": "9", "$text": "http://feeds.wnyc.org/studio360/podcast", "type": "Podcast", "title": "Studio 360"}, {"typeId": "9", "$text": "http://www.wnyc.org/feeds/series/lopate/underreported", "type": "Podcast", "title": "Underreported from The Leonard Lopate Show"}, {"typeId": "9", "$text": "http://feeds.wnyc.org/wnyc_soundcheck", "type": "Podcast", "title": "Soundcheck"}, {"typeId": "9", "$text": "http://feeds.wnyc.org/onthemedia", "type": "Podcast", "title": "On The Media from WNYC and NPR"}, {"typeId": "9", "$text": "http://feeds.wnyc.org/wnyc_bl", "type": "Podcast", "title": "The Brian Lehrer Show"}, {"typeId": "9", "$text": "http://feeds.wnyc.org/fishko", "type": "Podcast", "title": "Fishko Files"}, {"typeId": "9", "$text": "http://feeds.wnyc.org/wnyc_lopate", "type": "Podcast", "title": "The Leonard Lopate Show"}, {"typeId": "9", "$text": "http://feeds.wnyc.org/radiorookies", "type": "Podcast", "title": "Radio Rookies"}, {"typeId": "9", "$text": "http://feeds.wnyc.org/wnyc/news/local/rss", "type": "Podcast", "title": "News from WNYC New York Public Radio"}, {"typeId": "9", "$text": "http://feeds.wnyc.org/wnyc/newsounds", "type": "Podcast", "title": "New Sounds"}, {"typeId": "9", "$text": "http://feeds.wnyc.org/lastchancefoods", "type": "Podcast", "title": "Last Chance Foods"}, {"typeId": "9", "$text": "http://feeds.wnyc.org/talk_to_me", "type": "Podcast", "title": "Talk To Me"}, {"typeId": "9", "$text": "http://feeds.feedburner.com/freakonomicsradio", "type": "Podcast", "title": "Freakonomics Radio"}, {"typeId": "9", "$text": "http://feeds.wnyc.org/itsafreecountrypodcast", "type": "Podcast", "title": "It's A Free Country: The Podcast"}, {"typeId": "9", "$text": "http://feeds.wnyc.org/wnycheresthething/", "type": "Podcast", "title": "Here's The Thing"}, {"typeId": "9", "$text": "http://feeds.wnyc.org/money-talking", "type": "Podcast", "title": "Money Talking"}, {"typeId": "9", "$text": "http://feeds.wnyc.org/new-tech-city", "type": "Podcast", "title": "New Tech City"}, {"typeId": "10", "title": "WNYC-AM 820", "$text": "http://www.wnyc.org/stream/wnyc-am820/mp3.pls", "primary": "true", "guid": "4fcf71501b73444aa87f4dddb8165a39", "type": "Audio MP3 Stream"}, {"typeId": "10", "title": "WNYC-FM 93.9", "$text": "http://www.wnyc.org/stream/wnyc-fm939/mp3.pls", "primary": "false", "guid": "4fcf71501fed40a38998ea7960473a4a", "type": "Audio MP3 Stream"}, {"typeId": "13", "title": "WNYC-AM 820", "$text": "http://www.wnyc.org/stream/wnyc-am820/aac.pls", "primary": "true", "guid": "4fcf71501b73444aa87f4dddb8165a39", "type": "Audio AAC Stream"}, {"typeId": "13", "title": "WNYC-FM 93.9", "$text": "http://www.wnyc.org/stream/wnyc-fm939/aac.pls", "primary": "false", "guid": "4fcf71501fed40a38998ea7960473a4a", "type": "Audio AAC Stream"}, {"typeId": "15", "$text": "http://audio.wnyc.org/news/news_latest_newscast.mp3", "type": "Newscast", "title": "WNYC Newscast"}, {"typeId": "16", "$text": "http://www.facebook.com/wnyc", "type": "Facebook Url", "title": "Facebook"}, {"typeId": "17", "$text": "http://twitter.com/wnyc", "type": "Twitter Feed", "title": "Twitter"}], "tagline": [{"$text": "New York Public Radio"}], "signal": {"strength": "1", "$text": "weak"}, "memberStatus": {"$text": "Member"}, "band": {"$text": "AM"}, "state": {"$text": "NY"}, "frequency": {"$text": "820"}, "orgId": {"$text": "553"}, "image": [{"$text": "http://media.npr.org/images/stations/logos/wnyc_am.gif", "type": "logo"}], "marketCity": {"$text": "New York"}, "callLetters": {"$text": "WNYC"}, "coverage_url": {"$text": "/stations/station_xml/wnyc-am_820.xml"}, "guid": {"$text": "4fcf70111c344223a41a0d44bd1cfeab"}, "id": "553", "network": {"$text": "WNYC Radio", "orgId": "552"}}, {"orgDisplayName": {"$text": "WFUV On-Air: Rock and Roots Radio"}, "group": {"$text": "WFUV-FM", "id": "393"}, "name": {"$text": "WFUV-FM"}, "identifierAudioUrl": {"$text": "http://media.npr.org/stationid/393.mp4", "type": "mp4"}, "url": [{"typeId": "1", "$text": "http://www.wfuv.org", "type": "Organization Home Page", "title": "WFUV.org"}, {"typeId": "2", "$text": "http://www.publicbroadcasting.net/wfuv/guide.guidemain?t=1", "type": "Program Schedule", "title": "Program Guide"}, {"typeId": "4", "$text": "https://support.wfuv.org", "type": "Pledge Page", "title": "Support"}, {"typeId": "7", "$text": "http://www.wfuv.org/listen", "type": "Audio Stream Landing Page", "title": "WFUV New York: Listen Now"}, {"typeId": "7", "$text": "http://www.wfuv.org/listen", "type": "Audio Stream Landing Page", "title": "WFUV On-Air: Listen Now"}, {"typeId": "7", "$text": "http://www.thealternateside.org/audio-video/listen/", "type": "Audio Stream Landing Page", "title": "The Alternate Side: Listen Now"}, {"typeId": "9", "$text": "http://www.npr.org/templates/rss/podcast.php?id=510086", "type": "Podcast", "title": "WFUV-FM: WFUV's Cityscape Podcas"}, {"typeId": "9", "$text": "http://www.npr.org/templates/rss/podcast.php?id=510044", "type": "Podcast", "title": "WFUV-FM: WFUV's Take Five Podcast"}, {"typeId": "10", "title": "The Alternate Side", "$text": "http://www.wfuv.org/audio/altside128k.pls", "primary": "false", "guid": "4fcf715e0510443abc66dcb0e3e42e2f", "type": "Audio MP3 Stream"}, {"typeId": "10", "title": "WFUV On-Air: Rock and Roots Radio", "$text": "http://www.wfuv.org/sites/all/files/streams/wfuvmp3high.pls", "primary": "true", "guid": "13efb13be6f0117418e906a2db1d5eb9", "type": "Audio MP3 Stream"}, {"typeId": "10", "title": "WFUV All-Music: Rock and Roots Radio", "$text": "http://www.wfuv.org/sites/all/files/streams/fuv247_128k.pls", "primary": "false", "guid": "4fcf715e086d4cb9b6f8e5fbf3d5e83a", "type": "Audio MP3 Stream"}, {"typeId": "11", "title": "The Alternate Side", "$text": "http://www.wfuv.org/audio/altside.asx", "primary": "false", "guid": "4fcf715e0510443abc66dcb0e3e42e2f", "type": "Audio Windows Media Stream"}, {"typeId": "11", "title": "WFUV All-Music: Rock and Roots Radio", "$text": "http://www.wfuv.org/sites/all/files/streams/fuv247_32k.asx", "primary": "false", "guid": "4fcf715e086d4cb9b6f8e5fbf3d5e83a", "type": "Audio Windows Media Stream"}, {"typeId": "16", "$text": "http://www.facebook.com/WFUVPage", "type": "Facebook Url", "title": "Facebook"}, {"typeId": "17", "$text": "http://twitter.com/wfuv", "type": "Twitter Feed", "title": "Twitter"}], "tagline": [{"$text": "Public Radio from Fordham University in New York City"}], "signal": {"strength": "1", "$text": "weak"}, "memberStatus": {"$text": "Member"}, "band": {"$text": "FM"}, "state": {"$text": "NY"}, "frequency": {"$text": "90.7"}, "orgId": {"$text": "393"}, "image": [{"$text": "http://media.npr.org/images/stations/logos/wfuv_fm.gif", "type": "logo"}], "marketCity": {"$text": "New York"}, "callLetters": {"$text": "WFUV"}, "coverage_url": {"$text": "/stations/station_xml/wfuv-fm_90.7.xml"}, "guid": {"$text": "4fcf701019a245a8a623dfa08939deea"}, "id": "393"}, {"orgDisplayName": {"$text": "WRTI "}, "group": {"$text": "WRTI ", "id": "597"}, "name": {"$text": "WRTI-FM"}, "identifierAudioUrl": {"$text": "http://media.npr.org/stationid/597.mp4", "type": "mp4"}, "url": [{"typeId": "1", "$text": "http://www.wrti.org/", "type": "Organization Home Page", "title": "WRTI Homepage"}, {"typeId": "2", "$text": "http://www.wrti.org/schedule/wrti", "type": "Program Schedule", "title": "Program Schedule"}, {"typeId": "3", "$text": "http://astore.amazon.com/wwwwrtiorg-20", "type": "Online Store", "title": "WRTI Store"}, {"typeId": "4", "$text": "https://secure.publicbroadcasting.net/wrti/pledge.pledgemain", "type": "Pledge Page", "title": "Support WRTI"}, {"typeId": "7", "$text": "http://www.wrti.org/listen-live-wrti", "type": "Audio Stream Landing Page", "title": "WRTI Classical & Jazz"}, {"typeId": "7", "$text": "http://www.wrti.org/listen-live-wrti", "type": "Audio Stream Landing Page", "title": "WRTI Classical & Jazz"}, {"typeId": "10", "title": "WRTI Classical", "$text": "http://www.publicbroadcasting.net/wrti/ppr/wrti.m3u", "primary": "true", "guid": "4fcf7167072149d79cf30787888ac482", "type": "Audio MP3 Stream"}, {"typeId": "10", "title": "WRTI Jazz", "$text": "http://www.publicbroadcasting.net/wrti/ppr/wrti2.m3u", "primary": "false", "guid": "4fcf71670e8640288e97d8a2e62b66b1", "type": "Audio MP3 Stream"}, {"typeId": "16", "$text": "http://www.facebook.com/WRTImusic", "type": "Facebook Url", "title": "WRTImusic"}, {"typeId": "17", "$text": "http://twitter.com/wrtimusic", "type": "Twitter Feed", "title": "WRTImusic"}], "tagline": [{"$text": "Your Classical and Jazz Source"}], "signal": {"strength": "1", "$text": "weak"}, "memberStatus": {"$text": "Member"}, "band": {"$text": "FM"}, "state": {"$text": "PA"}, "frequency": {"$text": "90.1"}, "orgId": {"$text": "597"}, "image": [{"$text": "http://media.npr.org/images/stations/logos/wrti_fm.gif", "type": "logo"}], "marketCity": {"$text": "Philadelphia"}, "callLetters": {"$text": "WRTI"}, "coverage_url": {"$text": "/stations/station_xml/wrti-fm_90.1.xml"}, "guid": {"$text": "4fcf701125f1454d863af5005425aa76"}, "id": "597", "network": {"$text": "Temple University Public Radio", "orgId": "596"}}, {"orgDisplayName": {"$text": "Newark Public Radio"}, "group": {"$text": "Newark Public Radio", "id": "314"}, "name": {"$text": "WBGO-FM"}, "identifierAudioUrl": {"$text": "http://media.npr.org/stationid/314.mp4", "type": "mp4"}, "url": [{"typeId": "1", "$text": "http://www.wbgo.org", "type": "Organization Home Page", "title": "WBGO-FM Homepage"}, {"typeId": "2", "$text": "http://www.wbgo.org/schedule", "type": "Program Schedule", "title": "Program Schedule"}, {"typeId": "4", "$text": "https://www.wbgo.org/epledgenow/", "type": "Pledge Page", "title": "Become a Member of WBGO"}, {"typeId": "7", "$text": "http://www.wbgo.org/listennow/", "type": "Audio Stream Landing Page", "title": "88.3 WBGO: The Jazz Source"}, {"typeId": "7", "$text": "http://www.wbgo.org/internal/mediaplayer/?type=hd2", "type": "Audio Stream Landing Page", "title": "The Jazz Bee from WBGO"}, {"typeId": "8", "$text": "http://feeds.feedburner.com/WbgoNews/", "type": "RSS Feed", "title": "WBGO News"}, {"typeId": "10", "title": "88.3 WBGO: The Jazz Source", "$text": "http://wbgo.streamguys.net/listen.pls", "primary": "true", "guid": "4fcf714b0fed46aabb40d8dccfd2b653", "type": "Audio MP3 Stream"}, {"typeId": "10", "title": "The Jazz Bee from WBGO", "$text": "http://wbgo.streamguys.net/thejazzstream.pls", "primary": "false", "guid": "514afffb1a10483192fee5ed8c2888ba", "type": "Audio MP3 Stream"}, {"typeId": "15", "$text": "http://www.wbgo.org/nprmobile/wbgomobile.mp3", "type": "Newscast", "title": "WBGO-FM News"}, {"typeId": "16", "$text": "http://www.facebook.com/wbgojazz", "type": "Facebook Url", "title": "Facebook"}, {"typeId": "17", "$text": "http://www.twitter.com/wbgo", "type": "Twitter Feed", "title": "Twitter"}], "tagline": [{"$text": "The Jazz Source - on air, online, on your mobile device"}], "signal": {"strength": "1", "$text": "weak"}, "memberStatus": {"$text": "Member"}, "band": {"$text": "FM"}, "state": {"$text": "NJ"}, "frequency": {"$text": "88.3"}, "orgId": {"$text": "314"}, "image": [{"$text": "http://media.npr.org/images/stations/logos/wbgo_fm.gif", "type": "logo"}], "marketCity": {"$text": "Newark"}, "callLetters": {"$text": "WBGO"}, "coverage_url": {"$text": "/stations/station_xml/wbgo-fm_88.3.xml"}, "guid": {"$text": "4fcf701006234a26a2f8c9bcfddc462f"}, "id": "314", "network": {"$text": "Newark Public Radio", "orgId": "313"}}, {"orgDisplayName": {"$text": "XPN"}, "group": {"$text": "XPN", "id": "715"}, "name": {"$text": "WXPN-FM"}, "identifierAudioUrl": {"$text": "http://media.npr.org/stationid/715.mp4", "type": "mp4"}, "url": [{"typeId": "1", "$text": "http://www.xpn.org/", "type": "Organization Home Page", "title": "WXPN-FM Homepage"}, {"typeId": "2", "$text": "http://xpn.org/xpn-programs/program-guide", "type": "Program Schedule", "title": "Program Schedule"}, {"typeId": "4", "$text": "http://xpn.org/support-xpn/discover-membership", "type": "Pledge Page", "title": "Support WXPN"}, {"typeId": "7", "$text": "http://xpn.org/music-artist/xpn-stream", "type": "Audio Stream Landing Page", "title": "WXPN-FM 88.5"}, {"typeId": "7", "$text": "http://xpn.org/streams/xponential-radio", "type": "Audio Stream Landing Page", "title": "XPoNential Radio"}, {"typeId": "8", "$text": "http://wxpn.blogspot.com/atom.xml", "type": "RSS Feed", "title": "My Morning Download from WXPN"}, {"typeId": "8", "$text": "http://xpn.org/xpn_feed.xml", "type": "RSS Feed", "title": "WXPN All About The Music Feed"}, {"typeId": "8", "$text": "http://www.npr.org/rss/rss.php?id=39", "type": "RSS Feed", "title": "World Cafe with David Dye from WXPN"}, {"typeId": "8", "$text": "http://www.npr.org/rss/rss.php?id=5197069", "type": "RSS Feed", "title": "World Cafe: Next from WXPN"}, {"typeId": "9", "$text": "http://www.npr.org/rss/podcast.php?id=510165", "type": "Podcast", "title": "The Blues File from WXPN"}, {"typeId": "10", "title": "XPoNential Radio", "$text": "http://xpohi.streamguys.net/listen.pls", "primary": "false", "guid": "4fcf715321034201a25784c3dea4d8fe", "type": "Audio MP3 Stream"}, {"typeId": "10", "title": "WXPN-FM 88.5", "$text": "http://wxpnhi.streamguys.com/listen.pls", "primary": "true", "guid": "4fcf715317fe44b794b610e14c4fb34e", "type": "Audio MP3 Stream"}, {"typeId": "10", "title": "XPN2: Singer-Songwriter Radio", "$text": "http://xpn2lo.streamguys.net/listen.pls", "primary": "false", "guid": "13efb515e25035d44d6a940ffed563f0", "type": "Audio MP3 Stream"}, {"typeId": "11", "title": "WXPN-FM 88.5", "$text": "http://xpn-web.streamguys.com/xpn96a.asx", "primary": "true", "guid": "4fcf715317fe44b794b610e14c4fb34e", "type": "Audio Windows Media Stream"}, {"typeId": "11", "title": "XPN2: Singer-Songwriter Radio", "$text": "http://xpn-web.streamguys.com/xpn2lo.asx", "primary": "false", "guid": "13efb515e25035d44d6a940ffed563f0", "type": "Audio Windows Media Stream"}, {"typeId": "16", "$text": "http://www.facebook.com/pages/WXPN/32171784063", "type": "Facebook Url", "title": "Facebook"}, {"typeId": "17", "$text": "https://twitter.com/PhillyLocal", "type": "Twitter Feed", "title": "Twitter"}], "tagline": [{"$text": "It's All About the Music"}], "signal": {"strength": "1", "$text": "weak"}, "memberStatus": {"$text": "Member"}, "band": {"$text": "FM"}, "state": {"$text": "PA"}, "frequency": {"$text": "88.5"}, "orgId": {"$text": "715"}, "image": [{"$text": "http://media.npr.org/images/stations/logos/wxpn_fm.gif", "type": "logo"}], "marketCity": {"$text": "Philadelphia"}, "callLetters": {"$text": "WXPN"}, "coverage_url": {"$text": "/stations/station_xml/wxpn-fm_88.5.xml"}, "guid": {"$text": "4fcf70121a03434483a93d6e3c2dbdfd"}, "id": "715"}, {"orgDisplayName": {"$text": "90.5 The Night"}, "group": {"$text": "90.5 The Night", "id": "317"}, "name": {"$text": "WBJB-FM"}, "identifierAudioUrl": {"$text": "http://media.npr.org/stationid/317.mp4", "type": "mp4"}, "url": [{"typeId": "1", "$text": "http://www.90.5TheNIGHT.org", "type": "Organization Home Page", "title": "Brookdale Public Radio's  Homepage"}, {"typeId": "2", "$text": "http://wbjb.org/home.php/programs/", "type": "Program Schedule", "title": "Program Schedule"}, {"typeId": "4", "$text": "http://wbjb.org/pledge/", "type": "Pledge Page", "title": "Support"}, {"typeId": "7", "$text": "http://wbjb.org/home.php/listen/", "type": "Audio Stream Landing Page", "title": "90.5 The Night - WBJB-FM"}, {"typeId": "7", "$text": "http://wbjb.net", "type": "Audio Stream Landing Page", "title": "WBJB-FM Streams"}, {"typeId": "8", "$text": "http://wbjb.org/home.php/?feed=rss2", "type": "RSS Feed", "title": "Local News RSS"}, {"typeId": "8", "$text": "http://wbjb.org/home.php/?feed=rss2", "type": "RSS Feed", "title": "Odd News"}, {"typeId": "8", "$text": "http://wbjb.org/home.php/?feed=rss2", "type": "RSS Feed", "title": "On-Air Blog"}, {"typeId": "8", "$text": "http://www.wbjb.org/events/events/rss.php", "type": "RSS Feed", "title": "Events Calendar"}, {"typeId": "9", "$text": "http://wbjb.org/home.php/?feed=rss2", "type": "Podcast", "title": "Local News Podcast"}, {"typeId": "10", "title": "Altrok Radio 90.5 HD2", "$text": "http://wbjb.net:6192/listen.pls", "primary": "false", "guid": "514b000010c74d9d8b28368ffa2e15a8", "type": "Audio MP3 Stream"}, {"typeId": "10", "title": "Altrok Radio 90.5 HD2", "$text": "http://wbjb.net:6064/listen.pls", "primary": "false", "guid": "514b000010c74d9d8b28368ffa2e15a8", "type": "Audio MP3 Stream"}, {"typeId": "10", "title": "90.5 The Night - WBJB-FM", "$text": "http://wbjb.net:3056/listen.pls", "primary": "true", "guid": "4fcf7137219644b2a74cc3e8829c80dd", "type": "Audio MP3 Stream"}, {"typeId": "10", "title": "90.5 The Night - WBJB-FM", "$text": "http://wbjb.net:3256/listen.pls", "primary": "true", "guid": "4fcf7137219644b2a74cc3e8829c80dd", "type": "Audio MP3 Stream"}, {"typeId": "13", "title": "Altrok Radio 90.5 HD2", "$text": "http://wbjb.net:7032/listen.pls", "primary": "false", "guid": "514b000010c74d9d8b28368ffa2e15a8", "type": "Audio AAC Stream"}, {"typeId": "13", "title": "Altrok Radio 90.5 HD2", "$text": "http://wbjb.net:7056/listen.pls", "primary": "false", "guid": "514b000010c74d9d8b28368ffa2e15a8", "type": "Audio AAC Stream"}, {"typeId": "13", "title": "90.5 The Night - WBJB-FM", "$text": "http://wbjb.net:4064/listen.pls", "primary": "true", "guid": "4fcf7137219644b2a74cc3e8829c80dd", "type": "Audio AAC Stream"}, {"typeId": "13", "title": "90.5 The Night - WBJB-FM", "$text": "http://wbjb.net:4128/listen.pls", "primary": "true", "guid": "4fcf7137219644b2a74cc3e8829c80dd", "type": "Audio AAC Stream"}, {"typeId": "16", "$text": "https://www.facebook.com/BrookdalePublicRadio", "type": "Facebook Url", "title": "Facebook"}, {"typeId": "17", "$text": "https://twitter.com/wbjb", "type": "Twitter Feed", "title": "90.5 The Night"}], "tagline": [{"$text": "90.5 The Night"}], "signal": {"strength": "1", "$text": "weak"}, "memberStatus": {"$text": "Member"}, "band": {"$text": "FM"}, "state": {"$text": "NJ"}, "frequency": {"$text": "90.5"}, "orgId": {"$text": "317"}, "image": [{"$text": "http://media.npr.org/images/stations/logos/wbjb_fm.gif", "type": "logo"}], "marketCity": {"$text": "Lincroft"}, "callLetters": {"$text": "WBJB"}, "coverage_url": {"$text": "/stations/station_xml/wbjb-fm_90.5.xml"}, "guid": {"$text": "4fcf701006d640c8bb3351ea19a08c88"}, "id": "317", "network": {"$text": "Brookdale Public Radio", "orgId": "316"}}, {"orgDisplayName": {"$text": "WNYE"}, "group": {"$text": "WNYE-FM", "id": "555"}, "name": {"$text": "WNYE-FM"}, "identifierAudioUrl": {"$text": "http://media.npr.org/stationid/555.mp4", "type": "mp4"}, "url": [{"typeId": "1", "$text": "http://nyc.gov/html/media/html/radio/radio.shtml", "type": "Organization Home Page", "title": "WNYE-FM Homepage"}, {"typeId": "2", "$text": "http://www.nyc.gov/html/nycmg/wnyefm/html/schedule/schedule.shtml", "type": "Program Schedule", "title": "Program Schedule"}, {"typeId": "9", "$text": "http://www.nyc.gov/html/media/html/radio/radio_sidelines.shtml", "type": "Podcast", "title": "On the Sidelines with Vinny Aceto"}, {"typeId": "9", "$text": "http://www.npr.org/templates/rss/podcast.php?id=510175", "type": "Podcast", "title": "WNYE-FM: Digital Age Podcast"}, {"typeId": "9", "$text": "http://www.npr.org/templates/rss/podcast.php?id=510178", "type": "Podcast", "title": "WNYE-FM: The Gary Null Show Podcast"}, {"typeId": "9", "$text": "http://www.npr.org/templates/rss/podcast.php?id=510038", "type": "Podcast", "title": "WNYE-FM: The Leon Charney Report Podcast"}, {"typeId": "16", "$text": "http://www.facebook.com/pages/WNYE/108033125892008", "type": "Facebook Url", "title": "Facebook"}], "tagline": [{"$text": "WNYE-FM, New York"}], "signal": {"strength": "1", "$text": "weak"}, "memberStatus": {"$text": "Member"}, "band": {"$text": "FM"}, "state": {"$text": "NY"}, "frequency": {"$text": "91.5"}, "orgId": {"$text": "555"}, "image": [{"$text": "http://media.npr.org/images/stations/logos/wnye_fm.gif", "type": "logo"}], "marketCity": {"$text": "Brooklyn"}, "callLetters": {"$text": "WNYE"}, "coverage_url": {"$text": "/stations/station_xml/wnye-fm_91.5.xml"}, "guid": {"$text": "4fcf70111cae4398bc0ab64fd2ad350b"}, "id": "555"}, {"orgDisplayName": {"$text": "WWFM The Classical Network"}, "group": {"$text": "WWFM The Classical Network", "id": "918"}, "name": {"$text": "WWNJ-FM"}, "url": [{"typeId": "1", "$text": "http://www.wwfm.org/", "type": "Organization Home Page", "title": "WWNJ-FM Homepage"}, {"typeId": "2", "$text": "http://www.publicbroadcasting.net/wwfm/guide.guidemain", "type": "Program Schedule", "title": "Program Schedule"}, {"typeId": "4", "$text": "https://secure.publicbroadcasting.net/wwfm/form.pledgemain?action=pledge&pg=pledgeForm", "type": "Pledge Page", "title": "Support"}, {"typeId": "7", "$text": "http://www.wwfm.org/listen.shtml", "type": "Audio Stream Landing Page", "title": "WWFM Classical"}, {"typeId": "7", "$text": "http://www.wwfm.org/listen.shtml", "type": "Audio Stream Landing Page", "title": "WWFM Jazz"}, {"typeId": "10", "title": "WWFM Classical", "$text": "http://ice8.securenetsystems.net/WWFM.m3u", "primary": "true", "guid": "4fcf716a095d4478b136bea0b2f2fb91", "type": "Audio MP3 Stream"}, {"typeId": "10", "title": "WWFM Jazz", "$text": "http://ice8.securenetsystems.net/JAZZON2.m3u", "primary": "false", "guid": "4fcf716a0f3e4398bfab50a0246ace42", "type": "Audio MP3 Stream"}, {"typeId": "16", "$text": "http://www.facebook.com/pages/WWFM-The-Classical-Network/93029131926", "type": "Facebook Url", "title": "Facebook"}], "tagline": [{"$text": "WWFM The Classical Network"}], "signal": {"strength": "1", "$text": "weak"}, "memberStatus": {"$text": "Member"}, "band": {"$text": "FM"}, "state": {"$text": "NJ"}, "frequency": {"$text": "91.1"}, "orgId": {"$text": "977"}, "image": [{"$text": "http://media.npr.org/images/stations/logos/wwnj_fm.gif", "type": "logo"}], "marketCity": {"$text": "Dover Township"}, "callLetters": {"$text": "WWNJ"}, "coverage_url": {"$text": "/stations/station_xml/wwnj-fm_91.1.xml"}, "guid": {"$text": "4fcf701401aa4f87a6bc1738cf1c07ef"}, "id": "977", "network": {"$text": "WWFM-FM", "orgId": "918"}}, {"orgDisplayName": {"$text": "New Jersey Public Radio"}, "name": {"$text": "WNJO-FM"}, "url": [{"typeId": "1", "$text": "http://www.njpublicradio.org/", "type": "Organization Home Page", "title": "New Jersey Public Radio Homepage"}, {"typeId": "2", "$text": "http://www.njpublicradio.org/", "type": "Program Schedule", "title": "Program Schedule"}, {"typeId": "4", "$text": "https://pledge3.wnyc.org/epledge/desktop/njpr/?utm_source=npr&utm_medium=splash&utm_campaign=pledge&utm_content=njpr", "type": "Pledge Page", "title": "Support NJPR"}, {"typeId": "7", "$text": "http://www.njpublicradio.org/", "type": "Audio Stream Landing Page", "title": "NJPR"}, {"typeId": "10", "title": "NJPR", "$text": "http://wnyc-nj.streamguys.com/njprweb.m3u", "primary": "true", "guid": "4fcf715013c04799af5adece6a5e6404", "type": "Audio MP3 Stream"}], "tagline": [{}], "signal": {"strength": "1", "$text": "weak"}, "memberStatus": {"$text": "Member"}, "band": {"$text": "FM"}, "state": {"$text": "NJ"}, "frequency": {"$text": "90.3"}, "orgId": {"$text": "1245"}, "image": [{"$text": "http://media.npr.org/images/stations/logos/wnjo_fm.gif", "type": "logo"}], "marketCity": {"$text": "Toms River"}, "callLetters": {"$text": "WNJO"}, "coverage_url": {"$text": "/stations/station_xml/wnjo-fm_90.3.xml"}, "guid": {"$text": "4fcf701505d84fdfaf06093d4d6373d6"}, "id": "1245", "network": {"$text": "WNYC Radio", "orgId": "552"}}, {"orgDisplayName": {"$text": "WQXR radio"}, "name": {"$text": "WQXR-FM"}, "url": [{"typeId": "1", "$text": "http://www.wqxr.org", "type": "Organization Home Page", "title": "WQXR Home"}, {"typeId": "2", "$text": "http://www.wqxr.org/schedule/", "type": "Program Schedule", "title": "WQXR on air schedule"}, {"typeId": "4", "$text": "https://pledge3.wqxr.org/epledge/?utm_source=npr&utm_medium=link&utm_campaign=pledge&utm_content=wqxr", "type": "Pledge Page", "title": "105.9FM WQXR"}, {"typeId": "7", "$text": "http://www.wqxr.org", "type": "Audio Stream Landing Page", "title": "WQXR: New York's Classical Station"}, {"typeId": "7", "$text": "http://www.wqxr.org/q2", "type": "Audio Stream Landing Page", "title": "Q2: Living Music. Living Composers."}, {"typeId": "9", "$text": "http://www.wqxr.org/feeds/shows/wash-report", "type": "Podcast", "title": "The Washington Report"}, {"typeId": "9", "$text": "http://feeds.wnyc.org/aroundbroadway", "type": "Podcast", "title": "Around Broadway"}, {"typeId": "9", "$text": "http://feeds.wnyc.org/cafeconcerts", "type": "Podcast", "title": "Cafe Concerts"}, {"typeId": "9", "$text": "http://feeds.wnyc.org/conductingbusiness", "type": "Podcast", "title": "Conducting Business"}, {"typeId": "13", "title": "WQXR: New York's Classical Station", "$text": "http://www.wqxr.org/stream/wqxr/aac.pls", "primary": "true", "guid": "4fcf7151007341b7b570e4b15b3078c9", "type": "Audio AAC Stream"}, {"typeId": "13", "title": "Q2 Music: Living Music. Living Composers.", "$text": "http://www.wnyc.org/stream/q2/aac.pls ", "primary": "false", "guid": "4fcf7150247746b988de842a0dfe0c72", "type": "Audio AAC Stream"}, {"typeId": "13", "title": "WQXR: New York's Classical Station", "$text": "http://www.wqxr.org/stream/wqxr/aac.pls ", "primary": "true", "guid": "4fcf7151007341b7b570e4b15b3078c9", "type": "Audio AAC Stream"}, {"typeId": "16", "$text": "https://www.facebook.com/WQXRClassical", "type": "Facebook Url", "title": "Facebook"}, {"typeId": "17", "$text": "https://twitter.com/WQXR", "type": "Twitter Feed", "title": "Twitter"}], "tagline": [{"$text": "The Classical Music Station of NYC"}], "signal": {"strength": "1", "$text": "weak"}, "memberStatus": {"$text": "Member"}, "band": {"$text": "FM"}, "state": {"$text": "NJ"}, "frequency": {"$text": "105.9"}, "orgId": {"$text": "1130"}, "image": [{"$text": "http://media.npr.org/images/stations/logos/wqxr_fm.gif", "type": "logo"}], "marketCity": {"$text": "Newark"}, "callLetters": {"$text": "WQXR"}, "coverage_url": {"$text": "/stations/station_xml/wqxr-fm_105.9.xml"}, "guid": {"$text": "4fcf70141c6c4792b34b0c2d010ea015"}, "id": "1130", "network": {"$text": "WNYC Radio", "orgId": "552"}}, {"translator_band": {"$text": "FX"}, "name": {"$text": "WWFM-FM"}, "tagline": [{"$text": "WWFM The Classical Network"}], "signal": {"strength": "1", "$text": "weak"}, "memberStatus": {"$text": "Translator"}, "state": {"$text": "NJ"}, "band": {"$text": "FM"}, "translator_callLetters": {"$text": "W284BW"}, "frequency": {"$text": "104.7"}, "orgId": {"$text": "159405943"}, "image": [{"$text": "http://media.npr.org/images/stations/logos/wwfm_fm.gif", "type": "logo"}], "marketCity": {"$text": "Trenton"}, "callLetters": {"$text": "WWFM"}, "coverage_url": {"$text": "/stations/station_xml/wwfm-fm_104.7.w284bw-fx.xml"}, "guid": {"$text": "504786280ee34ddd956b1ba143f8a753"}, "orgDisplayName": {}, "id": "159405943", "network": {"$text": "WWFM-FM", "orgId": "918"}}, {"orgDisplayName": {"$text": "WNTI"}, "name": {"$text": "WNTI-FM"}, "url": [{"typeId": "1", "$text": "http://www.wnti.org", "type": "Organization Home Page", "title": "WNTI-FM Homepage"}, {"typeId": "2", "$text": "http://www.publicbroadcasting.net/wnti/guide.guidemain", "type": "Program Schedule", "title": "Program Guide"}, {"typeId": "4", "$text": "http://secure.publicbroadcasting.net/wnti/pledge.pledgemain", "type": "Pledge Page", "title": "Support"}], "tagline": [{"$text": "Public Radio from Centenary College"}], "signal": {"strength": "1", "$text": "weak"}, "memberStatus": {"$text": "Non-Member - NPR"}, "band": {"$text": "FM"}, "state": {"$text": "NJ"}, "frequency": {"$text": "91.9"}, "orgId": {"$text": "781"}, "image": [{"$text": "http://media.npr.org/images/stations/logos/wnti_fm.gif", "type": "logo"}], "marketCity": {"$text": "Hackettstown"}, "callLetters": {"$text": "WNTI"}, "coverage_url": {"$text": "/stations/station_xml/wnti-fm_91.9.xml"}, "guid": {"$text": "4fcf701301e54b71ae18cb0dfedf4fce"}, "id": "781"}, {"orgDisplayName": {}, "name": {"$text": "WBAI-FM"}, "tagline": [{}], "signal": {"strength": "1", "$text": "weak"}, "memberStatus": {"$text": "Non-Member"}, "band": {"$text": "FM"}, "state": {"$text": "NY"}, "frequency": {"$text": "99.5"}, "orgId": {"$text": "1262"}, "image": [{"$text": "http://media.npr.org/images/stations/logos/wbai_fm.gif", "type": "logo"}], "marketCity": {"$text": "New York"}, "callLetters": {"$text": "WBAI"}, "coverage_url": {"$text": "/stations/station_xml/wbai-fm_99.5.xml"}, "guid": {"$text": "4fcf70150a10467d905adecfc0a68287"}, "id": "1262"}], "version": "0.94", "title": {"$text": "Stations near 08570"}}