{"station": [{"orgDisplayName": {"$text": "WVIA"}, "group": {"$text": "WVIA-FM", "id": "678"}, "name": {"$text": "WVIA-FM"}, "identifierAudioUrl": {"$text": "http://media.npr.org/stationid/678.mp4", "type": "mp4"}, "url": [{"typeId": "1", "$text": "http://www.wvia.org/", "type": "Organization Home Page", "title": "WVIA-FM Homepage"}, {"typeId": "2", "$text": "http://www.publicbroadcasting.net/wvia/guide.guidemain", "type": "Program Schedule", "title": "Program Guide"}, {"typeId": "4", "$text": "http://wviatv.org/component/content/article/109-membership/293-pledge-now", "type": "Pledge Page", "title": "Support"}, {"typeId": "7", "$text": "http://www.publicbroadcasting.net/wvia/ppr/index.shtml", "type": "Audio Stream Landing Page", "title": "WVIA-FM"}, {"typeId": "7", "$text": "http://www.publicbroadcasting.net/wvia/ppr/index.shtml", "type": "Audio Stream Landing Page", "title": "WVIA-FM HD2"}, {"typeId": "7", "$text": "http://www.publicbroadcasting.net/wvia/ppr/index.shtml", "type": "Audio Stream Landing Page", "title": "WVIA-FM HD3"}, {"typeId": "9", "$text": "http://www.publicbroadcasting.net/wvia/.jukebox?action=featured", "type": "Podcast", "title": "ArtScene with Erika Funke"}, {"typeId": "10", "title": "WVIA-FM", "$text": "http://pubint.ic.llnwd.net/stream/pubint_wvia.pls", "primary": "true", "guid": "4fcf7168039242f3833378d4295b0bfa", "type": "Audio MP3 Stream"}, {"typeId": "10", "title": "WVIA-FM HD2", "$text": "http://pubint.ic.llnwd.net/stream/pubint_wvia2.pls", "primary": "false", "guid": "4fcf71680b7a4a0b838e349d18977e02", "type": "Audio MP3 Stream"}, {"typeId": "13", "title": "WVIA-FM HD3 - The Chiaroscuro Channel ", "$text": "http://stream.liquidcompass.net/WVIAHD3AAC.pls", "primary": "false", "guid": "13f1feffd5c00544adcb58fb15f6f42d", "type": "Audio AAC Stream"}, {"typeId": "16", "$text": "http://www.facebook.com/WVIATVFM", "type": "Facebook Url", "title": "Facebook"}, {"typeId": "17", "$text": "https://twitter.com/WVIATVFM", "type": "Twitter Feed", "title": "Twitter"}], "tagline": [{"$text": "Public Broadcasting for Northeastern Pennsylvania and the Central Susquehanna Valley"}], "signal": {"strength": "3", "$text": "moderate"}, "memberStatus": {"$text": "Member"}, "band": {"$text": "FM"}, "state": {"$text": "PA"}, "frequency": {"$text": "89.9"}, "orgId": {"$text": "678"}, "image": [{"$text": "http://media.npr.org/images/stations/logos/wvia_fm.gif", "type": "logo"}], "marketCity": {"$text": "Scranton"}, "callLetters": {"$text": "WVIA"}, "coverage_url": {"$text": "/stations/station_xml/wvia-fm_89.9.xml"}, "guid": {"$text": "4fcf7012126b4c52b551748ddfb452a4"}, "id": "678", "network": {"$text": "WVIA Public Broadcasting", "orgId": "677"}}, {"orgDisplayName": {"$text": "WHYY"}, "group": {"$text": "WHYY-FM", "id": "433"}, "name": {"$text": "WHYY-FM"}, "identifierAudioUrl": {"$text": "http://media.npr.org/stationid/433.mp4", "type": "mp4"}, "url": [{"typeId": "1", "$text": "http://www.whyy.org/91FM/index.php", "type": "Organization Home Page", "title": "WHYY-FM Homepage"}, {"typeId": "2", "$text": "http://www.whyy.org/91FM/schedule.php", "type": "Program Schedule", "title": "Program Schedule"}, {"typeId": "4", "$text": "http://www.whyy.org/support/", "type": "Pledge Page", "title": "Support WHYY"}, {"typeId": "7", "$text": "http://www.whyy.org/91FM/live.php", "type": "Audio Stream Landing Page", "title": "WHYY-FM Listen Live"}, {"typeId": "7", "$text": "http://www.whyy.org/91FM/live.php", "type": "Audio Stream Landing Page", "title": "WHYY - Second Audio Program"}, {"typeId": "9", "$text": "http://www.whyy.org/rss/voices.xml", "type": "Podcast", "title": "WHYY's Voices in the Family"}, {"typeId": "9", "$text": "http://www.whyy.org/rss/garden.xml", "type": "Podcast", "title": "You Bet Your Garden"}, {"typeId": "9", "$text": "http://feeds.feedburner.com/NewsWorksTonight", "type": "Podcast", "title": "NewsWorks Tonight"}, {"typeId": "9", "$text": "http://www.whyy.org/rss/skytalk.xml", "type": "Podcast", "title": "Skytalk"}, {"typeId": "9", "$text": "http://www.npr.org/templates/rss/podcast.php?id=510027", "type": "Podcast", "title": "WHYY-FM: Radio Times Podcast"}, {"typeId": "10", "title": "WHYY - Second Audio Program", "$text": "http://207.245.67.206/listen.pls", "primary": "false", "guid": "4fcf7169163947a3a99a9cd9770cc6d7", "type": "Audio MP3 Stream"}, {"typeId": "10", "title": "WHYY-FM Listen Live", "$text": "http://207.245.67.209/91FM.m3u", "primary": "true", "guid": "4fcf713517374aeea549cae46ed92e27", "type": "Audio MP3 Stream"}, {"typeId": "11", "title": "WHYY-FM Listen Live", "$text": "http://www.whyy.org/91FM/whyy.asx", "primary": "true", "guid": "4fcf713517374aeea549cae46ed92e27", "type": "Audio Windows Media Stream"}, {"typeId": "12", "$text": "http://www.whyy.org/91FM/live40.ram", "type": "Audio Real Media Stream", "title": "WHYY-FM Listen Live"}, {"typeId": "15", "$text": "http://www.whyy.org/podcast/whyy_newscast.mp3", "type": "Newscast", "title": "WHYY-FM News"}, {"typeId": "16", "$text": "http://www.facebook.com/whyypublicmedia", "type": "Facebook Url", "title": "Facebook"}, {"typeId": "17", "$text": "http://www.twitter.com/whyy", "type": "Twitter Feed", "title": "Twitter"}], "tagline": [{"$text": "Public Media Serving Southeastern Pennsylvania, Delaware, South Jersey and the world"}], "signal": {"strength": "1", "$text": "weak"}, "memberStatus": {"$text": "Member"}, "band": {"$text": "FM"}, "state": {"$text": "PA"}, "frequency": {"$text": "90.9"}, "orgId": {"$text": "433"}, "image": [{"$text": "http://media.npr.org/images/stations/logos/whyy_fm.gif", "type": "logo"}], "marketCity": {"$text": "Philadelphia"}, "callLetters": {"$text": "WHYY"}, "coverage_url": {"$text": "/stations/station_xml/whyy-fm_90.9.xml"}, "guid": {"$text": "4fcf701025bc43a0b6fd7dd8d6dcd418"}, "id": "433", "network": {"$text": "WHYY, Inc.", "orgId": "432"}}, {"orgDisplayName": {"$text": "WITF"}, "group": {"$text": "WITF-FM", "id": "442"}, "name": {"$text": "WITF-FM"}, "identifierAudioUrl": {"$text": "http://media.npr.org/stationid/442.mp4", "type": "mp4"}, "url": [{"typeId": "1", "$text": "http://www.witf.org/", "type": "Organization Home Page", "title": "witf Homepage"}, {"typeId": "2", "$text": "http://www.witf.org/listen/radio-schedule.php", "type": "Program Schedule", "title": "Radio schedules"}, {"typeId": "4", "$text": "https://netcommunity.witf.org/donation/pledge", "type": "Pledge Page", "title": "Support witf"}, {"typeId": "7", "$text": "http://www.witf.org/listen", "type": "Audio Stream Landing Page", "title": "witf news and information"}, {"typeId": "8", "$text": "http://feeds.witf.org/witf-news", "type": "RSS Feed", "title": "witf News Feed"}, {"typeId": "9", "$text": "http://www.witf.org/smart-talk/feed/rss", "type": "Podcast", "title": "Smart Talk"}, {"typeId": "10", "title": "witf news and information", "$text": "http://witf.ic.llnwd.net/stream/witf_mp3.pls", "primary": "true", "guid": "514afff40c154f11b768b1592bb7648c", "type": "Audio MP3 Stream"}, {"typeId": "11", "title": "witf news and information", "$text": "http://www.witf.org/listen/witf_wm.asx", "primary": "true", "guid": "13d8e8e96c300d34e5aba99186f8f4ef", "type": "Audio Windows Media Stream"}, {"typeId": "16", "$text": "http://www.facebook.com/witf.org", "type": "Facebook Url", "title": "Facebook"}, {"typeId": "17", "$text": "http://www.twitter.com/witfnews", "type": "Twitter Feed", "title": "witf News "}], "tagline": [{"$text": "Your Home for NPR News and All Things Regional"}], "signal": {"strength": "1", "$text": "weak"}, "memberStatus": {"$text": "Member"}, "band": {"$text": "FM"}, "state": {"$text": "PA"}, "frequency": {"$text": "89.5"}, "orgId": {"$text": "442"}, "image": [{"$text": "http://media.npr.org/images/stations/logos/witf_fm.gif", "type": "logo"}], "marketCity": {"$text": "Harrisburg"}, "callLetters": {"$text": "WITF"}, "coverage_url": {"$text": "/stations/station_xml/witf-fm_89.5.xml"}, "guid": {"$text": "4fcf701100e64122b28ba5bf7a3e61d0"}, "id": "442"}, {"orgDisplayName": {"$text": "WRTI "}, "group": {"$text": "WRTI ", "id": "597"}, "name": {"$text": "WRTI-FM"}, "identifierAudioUrl": {"$text": "http://media.npr.org/stationid/597.mp4", "type": "mp4"}, "url": [{"typeId": "1", "$text": "http://www.wrti.org/", "type": "Organization Home Page", "title": "WRTI Homepage"}, {"typeId": "2", "$text": "http://www.wrti.org/schedule/wrti", "type": "Program Schedule", "title": "Program Schedule"}, {"typeId": "3", "$text": "http://astore.amazon.com/wwwwrtiorg-20", "type": "Online Store", "title": "WRTI Store"}, {"typeId": "4", "$text": "https://secure.publicbroadcasting.net/wrti/pledge.pledgemain", "type": "Pledge Page", "title": "Support WRTI"}, {"typeId": "7", "$text": "http://www.wrti.org/listen-live-wrti", "type": "Audio Stream Landing Page", "title": "WRTI Classical & Jazz"}, {"typeId": "7", "$text": "http://www.wrti.org/listen-live-wrti", "type": "Audio Stream Landing Page", "title": "WRTI Classical & Jazz"}, {"typeId": "10", "title": "WRTI Classical", "$text": "http://www.publicbroadcasting.net/wrti/ppr/wrti.m3u", "primary": "true", "guid": "4fcf7167072149d79cf30787888ac482", "type": "Audio MP3 Stream"}, {"typeId": "10", "title": "WRTI Jazz", "$text": "http://www.publicbroadcasting.net/wrti/ppr/wrti2.m3u", "primary": "false", "guid": "4fcf71670e8640288e97d8a2e62b66b1", "type": "Audio MP3 Stream"}, {"typeId": "16", "$text": "http://www.facebook.com/WRTImusic", "type": "Facebook Url", "title": "WRTImusic"}, {"typeId": "17", "$text": "http://twitter.com/wrtimusic", "type": "Twitter Feed", "title": "WRTImusic"}], "tagline": [{"$text": "Your Classical and Jazz Source"}], "signal": {"strength": "1", "$text": "weak"}, "memberStatus": {"$text": "Member"}, "band": {"$text": "FM"}, "state": {"$text": "PA"}, "frequency": {"$text": "90.1"}, "orgId": {"$text": "597"}, "image": [{"$text": "http://media.npr.org/images/stations/logos/wrti_fm.gif", "type": "logo"}], "marketCity": {"$text": "Philadelphia"}, "callLetters": {"$text": "WRTI"}, "coverage_url": {"$text": "/stations/station_xml/wrti-fm_90.1.xml"}, "guid": {"$text": "4fcf701125f1454d863af5005425aa76"}, "id": "597", "network": {"$text": "Temple University Public Radio", "orgId": "596"}}, {"orgDisplayName": {"$text": "WRTI "}, "group": {"$text": "WRTI ", "id": "597"}, "name": {"$text": "WJAZ-FM"}, "url": [{"typeId": "1", "$text": "http://www.wrti.org/", "type": "Organization Home Page", "title": "WRTI Homepage"}, {"typeId": "2", "$text": "http://www.wrti.org/schedule/week/wrti", "type": "Program Schedule", "title": "Program Schedule"}, {"typeId": "3", "$text": "http://astore.amazon.com/wwwwrtiorg-20", "type": "Online Store", "title": "WRTI Store"}, {"typeId": "4", "$text": "https://secure.publicbroadcasting.net/wrti/pledge.pledgemain", "type": "Pledge Page", "title": "Support WRTI"}, {"typeId": "7", "$text": "http://www.wrti.org/listen-live-wrti", "type": "Audio Stream Landing Page", "title": "WRTI Classical & Jazz"}, {"typeId": "7", "$text": "http://www.wrti.org/listen-live-wrti", "type": "Audio Stream Landing Page", "title": "WRTI Classical & Jazz"}, {"typeId": "10", "title": "WRTI Classical", "$text": "http://www.publicbroadcasting.net/wrti/ppr/wrti.m3u", "primary": "true", "guid": "4fcf7167072149d79cf30787888ac482", "type": "Audio MP3 Stream"}, {"typeId": "10", "title": "WRTI Jazz", "$text": "http://www.publicbroadcasting.net/wrti/ppr/wrti2.m3u", "primary": "false", "guid": "4fcf71670e8640288e97d8a2e62b66b1", "type": "Audio MP3 Stream"}, {"typeId": "16", "$text": "http://www.facebook.com/WRTImusic", "type": "Facebook Url", "title": "WRTImusic"}, {"typeId": "17", "$text": "http://twitter.com/wrtimusic", "type": "Twitter Feed", "title": "WRTImusic"}], "tagline": [{"$text": "Your Member-Supported Classical & Jazz Source"}], "signal": {"strength": "1", "$text": "weak"}, "memberStatus": {"$text": "Member"}, "band": {"$text": "FM"}, "state": {"$text": "PA"}, "frequency": {"$text": "91.7"}, "orgId": {"$text": "598"}, "image": [{"$text": "http://media.npr.org/images/stations/logos/wjaz_fm.gif", "type": "logo"}], "marketCity": {"$text": "Summerdale"}, "callLetters": {"$text": "WJAZ"}, "coverage_url": {"$text": "/stations/station_xml/wjaz-fm_91.7.xml"}, "guid": {"$text": "4fcf7011262d47378a7e50fb335975f7"}, "id": "598", "network": {"$text": "Temple University Public Radio", "orgId": "596"}}, {"orgDisplayName": {"$text": "WRTI"}, "name": {"$text": "WRTL-FM"}, "url": [{"typeId": "1", "$text": "http://www.wrti.org", "type": "Organization Home Page", "title": "WRTI Homepage"}, {"typeId": "2", "$text": "http://www.wrti.org/schedule/week/wrti", "type": "Program Schedule", "title": "Program Schedule"}, {"typeId": "3", "$text": "http://astore.amazon.com/wwwwrtiorg-20", "type": "Online Store", "title": "WRTI Store"}, {"typeId": "4", "$text": "https://secure.publicbroadcasting.net/wrti/pledge.pledgemain", "type": "Pledge Page", "title": "Support WRTI"}, {"typeId": "7", "$text": "http://www.wrti.org/listen-live-wrti", "type": "Audio Stream Landing Page", "title": "WRTI Classical & Jazz"}, {"typeId": "15", "$text": "http://twitter.com/wrtimusic", "type": "Newscast", "title": "WRTImusic"}, {"typeId": "16", "$text": "http://www.facebook.com/WRTImusic", "type": "Facebook Url", "title": "WRTImusic"}, {"typeId": "17", "$text": "http://twitter.com/wrtimusic", "type": "Twitter Feed", "title": "WRTImusic"}], "tagline": [{"$text": "Your Member-Supported Classical & Jazz Source"}], "signal": {"strength": "1", "$text": "weak"}, "memberStatus": {"$text": "Member"}, "band": {"$text": "FM"}, "state": {"$text": "PA"}, "frequency": {"$text": "90.7"}, "orgId": {"$text": "1149"}, "image": [{"$text": "http://media.npr.org/images/stations/logos/wrtl_fm.gif", "type": "logo"}], "marketCity": {"$text": "Ephrata"}, "callLetters": {"$text": "WRTL"}, "coverage_url": {"$text": "/stations/station_xml/wrtl-fm_90.7.xml"}, "guid": {"$text": "4fcf70141f3a417e8134b02d149e706b"}, "id": "1149", "network": {"$text": "Temple University Public Radio", "orgId": "596"}}, {"translator_band": {"$text": "FX"}, "name": {"$text": "WVIA-FM"}, "tagline": [{"$text": "Public Broadcasting for Northeastern Pennsylvania and the Central Susquehanna Valley"}], "signal": {"strength": "1", "$text": "weak"}, "memberStatus": {"$text": "Translator"}, "state": {"$text": "PA"}, "band": {"$text": "FM"}, "translator_callLetters": {"$text": "W235AD"}, "frequency": {"$text": "94.9"}, "orgId": {"$text": "5131345"}, "image": [{"$text": "http://media.npr.org/images/stations/logos/wvia_fm.gif", "type": "logo"}], "marketCity": {"$text": "Scranton"}, "callLetters": {"$text": "WVIA"}, "coverage_url": {"$text": "/stations/station_xml/wvia-fm_94.9.w235ad-fx.xml"}, "guid": {"$text": "503e27e5016d4d379dca96f13e866c1c"}, "orgDisplayName": {"$text": "WVIA"}, "id": "5131345", "network": {"$text": "WVIA Public Broadcasting", "orgId": "677"}}, {"translator_band": {"$text": "FX"}, "name": {"$text": "WRTY-FM"}, "tagline": [{"$text": "Your Member-Supported Classical & Jazz Source"}], "signal": {"strength": "1", "$text": "weak"}, "memberStatus": {"$text": "Translator"}, "state": {"$text": "PA"}, "band": {"$text": "FM"}, "translator_callLetters": {"$text": "W256AB"}, "frequency": {"$text": "99.1"}, "orgId": {"$text": "5131368"}, "image": [{"$text": "http://media.npr.org/images/stations/logos/wrty_fm.gif", "type": "logo"}], "marketCity": {"$text": "Mt. Pocono"}, "callLetters": {"$text": "WRTY"}, "coverage_url": {"$text": "/stations/station_xml/wrty-fm_99.1.w256ab-fx.xml"}, "guid": {"$text": "503e2a960fa64507a07c87e2fa9daaaa"}, "orgDisplayName": {"$text": "WRTI "}, "id": "5131368", "network": {"$text": "Temple University Public Radio", "orgId": "596"}}], "version": "0.94", "title": {"$text": "Stations near 17920"}}