{"station": [{"orgDisplayName": {"$text": "WHQR"}, "group": {"$text": "WHQR-FM", "id": "429"}, "name": {"$text": "WHQR-FM"}, "identifierAudioUrl": {"$text": "http://media.npr.org/stationid/429.mp4", "type": "mp4"}, "url": [{"typeId": "1", "$text": "http://www.whqr.org", "type": "Organization Home Page", "title": "WHQR Homepage"}, {"typeId": "2", "$text": "http://whqr.org/schedule/week", "type": "Program Schedule", "title": "Program Schedule"}, {"typeId": "4", "$text": "http://whqr.org/pledge-now", "type": "Pledge Page", "title": "Support"}, {"typeId": "7", "$text": "http://www.whqr.org", "type": "Audio Stream Landing Page", "title": "WHQR - NPR News and Music from the Cape Fear Region"}, {"typeId": "7", "$text": "http://www.whqr.org", "type": "Audio Stream Landing Page", "title": "WHQR Classical HD-2"}, {"typeId": "8", "$text": "http://www.whqr.org/feeds/term/61/rss.xml", "type": "RSS Feed", "title": "Local News"}, {"typeId": "8", "$text": "http://www.whqr.org/feeds/term/19/rss.xml", "type": "RSS Feed", "title": "Inside WHQR"}, {"typeId": "10", "title": "WHQR - NPR News and Music from the Cape Fear Region", "$text": "http://www.publicbroadcasting.net/whqr/ppr/whqr.m3u", "primary": "true", "guid": "4fcf71641edb4057ade2e191e1bacd25", "type": "Audio MP3 Stream"}, {"typeId": "10", "$text": "http://whqr.org/sites/whqr/files/streaming/whqr_hd2_0.m3u", "type": "Audio MP3 Stream", "title": "WHQR Classical HD-2"}, {"typeId": "16", "$text": "http://www.facebook.com/WHQRPublicRadio", "type": "Facebook Url", "title": "Facebook"}, {"typeId": "17", "$text": "https://twitter.com/whqr", "type": "Twitter Feed", "title": "Twitter"}], "tagline": [{"$text": "Radio with Vision...Listen and See"}], "signal": {"strength": "5", "$text": "strong"}, "memberStatus": {"$text": "Member"}, "band": {"$text": "FM"}, "state": {"$text": "NC"}, "frequency": {"$text": "91.3"}, "orgId": {"$text": "429"}, "image": [{"$text": "http://media.npr.org/images/stations/logos/whqr_fm.gif", "type": "logo"}], "marketCity": {"$text": "Wilmington"}, "callLetters": {"$text": "WHQR"}, "coverage_url": {"$text": "/stations/station_xml/whqr-fm_91.3.xml"}, "guid": {"$text": "4fcf701024c64bbd9932ce41c41a5292"}, "id": "429"}], "version": "0.94", "title": {"$text": "Stations near 28402"}}