{"station": [{"translator_band": {"$text": "FX"}, "name": {"$text": "KCBX-FM"}, "tagline": [{"$text": "Listener Supported in San Luis Obispo, Santa Barbara and Monterey Counties"}], "signal": {"strength": "5", "$text": "strong"}, "memberStatus": {"$text": "Translator"}, "state": {"$text": "CA"}, "band": {"$text": "FM"}, "translator_callLetters": {"$text": "K215AF"}, "frequency": {"$text": "90.9"}, "orgId": {"$text": "5130935"}, "image": [{"$text": "http://media.npr.org/images/stations/logos/kcbx_fm.gif", "type": "logo"}], "marketCity": {"$text": "San Luis Obispo"}, "callLetters": {"$text": "KCBX"}, "coverage_url": {"$text": "/stations/station_xml/kcbx-fm_90.9.k215af-fx.xml"}, "guid": {"$text": "503cea581b8d47e68edff1018a2ceaf4"}, "orgDisplayName": {"$text": "KCBX"}, "id": "5130935", "network": {"$text": "KCBX-FM", "orgId": "27"}}, {"orgDisplayName": {"$text": "KCBX"}, "group": {"$text": "KCBX-FM", "id": "27"}, "name": {"$text": "KCBX-FM"}, "identifierAudioUrl": {"$text": "http://media.npr.org/stationid/27.mp4", "type": "mp4"}, "url": [{"typeId": "1", "$text": "http://www.kcbx.org", "type": "Organization Home Page", "title": "KCBX-FM Homepage"}, {"typeId": "2", "$text": "http://www.kcbx.org/Pages/Programming/music_playlists.html?CMD=SCHEDULE", "type": "Program Schedule", "title": "Program Schedule"}, {"typeId": "4", "$text": "https://www.kcbx.org/ecommerce/WebOrder_PL1.php", "type": "Pledge Page", "title": "Pledge Online"}, {"typeId": "7", "$text": "http://www.kcbx.org/Pages/Programming/listen_live.html", "type": "Audio Stream Landing Page", "title": "KCBX-FM"}, {"typeId": "9", "$text": "http://www.npr.org/templates/rss/podcast.php?id=510189", "type": "Podcast", "title": "KCBX-FM: An Evening With... Podcast"}, {"typeId": "9", "$text": "http://www.npr.org/templates/rss/podcast.php?id=510074", "type": "Podcast", "title": "KCBX-FM: Audio Log Podcast"}, {"typeId": "10", "title": "KCBX-FM", "$text": "http://peace.str3am.com:6410/listen.pls", "primary": "true", "guid": "4fcf714425ab451e877ff69f1355de8d", "type": "Audio MP3 Stream"}], "tagline": [{"$text": "Listener Supported in San Luis Obispo, Santa Barbara and Monterey Counties"}], "signal": {"strength": "3", "$text": "moderate"}, "memberStatus": {"$text": "Member"}, "band": {"$text": "FM"}, "state": {"$text": "CA"}, "frequency": {"$text": "90.1"}, "orgId": {"$text": "27"}, "image": [{"$text": "http://media.npr.org/images/stations/logos/kcbx_fm.gif", "type": "logo"}], "marketCity": {"$text": "San Luis Obispo"}, "callLetters": {"$text": "KCBX"}, "coverage_url": {"$text": "/stations/station_xml/kcbx-fm_90.1.xml"}, "guid": {"$text": "4fcf700e0563432d9fb41d500d95c722"}, "id": "27"}, {"orgDisplayName": {}, "name": {"$text": "KNBX-FM"}, "tagline": [{}], "signal": {"strength": "3", "$text": "moderate"}, "memberStatus": {"$text": "Member"}, "band": {"$text": "FM"}, "state": {"$text": "CA"}, "frequency": {"$text": "91.7"}, "orgId": {"$text": "1127"}, "image": [{"$text": "http://media.npr.org/images/stations/logos/knbx_fm.gif", "type": "logo"}], "marketCity": {"$text": "San Ardo"}, "callLetters": {"$text": "KNBX"}, "coverage_url": {"$text": "/stations/station_xml/knbx-fm_91.7.xml"}, "guid": {"$text": "4fcf70141c264738a931502536da0aba"}, "id": "1127", "network": {"$text": "KCBX-FM", "orgId": "27"}}, {"orgDisplayName": {}, "name": {"$text": "KESC-FM"}, "url": [{"typeId": "1", "$text": "http://www.kusc.org", "type": "Organization Home Page", "title": "Classical KUSC"}, {"typeId": "2", "$text": "http://www.kusc.org/programs/schedule.aspx", "type": "Program Schedule", "title": "Program Schedule"}, {"typeId": "4", "$text": "http://kuscinteractive.org/donate", "type": "Pledge Page", "title": "Support KUSC"}, {"typeId": "7", "$text": "http://www.kusc.org/listenonline/index.aspx", "type": "Audio Stream Landing Page", "title": "Classical KUSC"}, {"typeId": "11", "title": "Classical KUSC", "$text": "http://kuscstream.org/wmp/kusc128.asx", "primary": "true", "guid": "4fcf713f050840628c2287a9f489dc67", "type": "Audio Windows Media Stream"}, {"typeId": "12", "title": "Classical KUSC", "$text": "http://kuscstream.org/real/kusc128.ram", "primary": "true", "guid": "4fcf713f050840628c2287a9f489dc67", "type": "Audio Real Media Stream"}, {"typeId": "13", "title": "Classical KUSC", "$text": "http://kusc-ice.streamguys.com/kusc-96k.m3u", "primary": "true", "guid": "4fcf713f050840628c2287a9f489dc67", "type": "Audio AAC Stream"}, {"typeId": "16", "$text": "http://www.facebook.com/pages/Classical-KUSC/106866573230", "type": "Facebook Url", "title": "Facebook"}], "tagline": [{"$text": "Classical KUSC"}], "signal": {"strength": "1", "$text": "weak"}, "memberStatus": {"$text": "Member"}, "band": {"$text": "FM"}, "state": {"$text": "CA"}, "frequency": {"$text": "99.7"}, "orgId": {"$text": "1132"}, "image": [{"$text": "http://media.npr.org/images/stations/logos/kesc_fm.gif", "type": "logo"}], "marketCity": {"$text": "Morro Bay"}, "callLetters": {"$text": "KESC"}, "coverage_url": {"$text": "/stations/station_xml/kesc-fm_99.7.xml"}, "guid": {"$text": "4fcf70141cdd438d985bd5e95355013b"}, "id": "1132", "network": {"$text": "KUSC-FM", "orgId": "233"}}, {"orgDisplayName": {}, "name": {"$text": "KCLM-FM"}, "tagline": [{}], "signal": {"strength": "1", "$text": "weak"}, "memberStatus": {"$text": "Member"}, "band": {"$text": "FM"}, "state": {"$text": "CA"}, "frequency": {"$text": "89.7"}, "orgId": {"$text": "1385"}, "image": [{"$text": "http://media.npr.org/images/stations/logos/kclm_fm.gif", "type": "logo"}], "marketCity": {"$text": "Santa Maria"}, "callLetters": {"$text": "KCLM"}, "coverage_url": {"$text": "/stations/station_xml/kclm-fm_89.7.xml"}, "guid": {"$text": "51af476117c943a19635125c4bccceda"}, "id": "1385", "network": {"$text": "KCLU-FM", "orgId": "45"}}, {"translator_band": {"$text": "FX"}, "name": {"$text": "KCBX-FM"}, "tagline": [{"$text": "Listener Supported in San Luis Obispo, Santa Barbara and Monterey Counties"}], "signal": {"strength": "1", "$text": "weak"}, "memberStatus": {"$text": "Translator"}, "state": {"$text": "CA"}, "band": {"$text": "FM"}, "translator_callLetters": {"$text": "K216AG"}, "frequency": {"$text": "91.1"}, "orgId": {"$text": "5130965"}, "image": [{"$text": "http://media.npr.org/images/stations/logos/kcbx_fm.gif", "type": "logo"}], "marketCity": {"$text": "San Luis Obispo"}, "callLetters": {"$text": "KCBX"}, "coverage_url": {"$text": "/stations/station_xml/kcbx-fm_91.1.k216ag-fx.xml"}, "guid": {"$text": "503ceac70f4f4e588bc795f234f3f16b"}, "orgDisplayName": {"$text": "KCBX"}, "id": "5130965", "network": {"$text": "KCBX-FM", "orgId": "27"}}], "version": "0.94", "title": {"$text": "Stations near 93428"}}