{"station": [{"orgDisplayName": {"$text": "KHSU"}, "group": {"$text": "KHSU-FM", "id": "92"}, "name": {"$text": "KHSU-FM"}, "identifierAudioUrl": {"$text": "http://media.npr.org/stationid/92.mp4", "type": "mp4"}, "url": [{"typeId": "1", "$text": "http://www.khsu.org/", "type": "Organization Home Page", "title": "KHSU-FM Homepage"}, {"typeId": "2", "$text": "http://www.khsu.org/program_grid", "type": "Program Schedule", "title": "Program Schedule"}, {"typeId": "4", "$text": "http://www.khsu.org/why_donate", "type": "Pledge Page", "title": "Support"}, {"typeId": "7", "$text": "http://www.khsu.org/listen_live", "type": "Audio Stream Landing Page", "title": "KHSU-FM"}, {"typeId": "10", "title": "KHSU-FM", "$text": "http://peace.str3am.com:6650/listen.pls", "primary": "true", "guid": "4fcf7145020e4bd398c971c018a107c7", "type": "Audio MP3 Stream"}, {"typeId": "16", "$text": "http://www.facebook.com/905KHSU", "type": "Facebook Url", "title": "Facebook"}, {"typeId": "17", "$text": "http://twitter.com/905KHSU ", "type": "Twitter Feed", "title": "Twitter"}], "tagline": [{"$text": "Diverse Public Radio"}], "signal": {"strength": "5", "$text": "strong"}, "memberStatus": {"$text": "Member"}, "band": {"$text": "FM"}, "state": {"$text": "CA"}, "frequency": {"$text": "90.5"}, "orgId": {"$text": "92"}, "image": [{"$text": "http://media.npr.org/images/stations/logos/khsu_fm.gif", "type": "logo"}], "marketCity": {"$text": "Arcata"}, "callLetters": {"$text": "KHSU"}, "coverage_url": {"$text": "/stations/station_xml/khsu-fm_90.5.xml"}, "guid": {"$text": "4fcf700e191b4c5cb5fce7b5a92203ad"}, "id": "92"}, {"orgDisplayName": {}, "name": {"$text": "KMUE-FM"}, "tagline": [{}], "signal": {"strength": "5", "$text": "strong"}, "memberStatus": {"$text": "Non-Member"}, "band": {"$text": "FM"}, "state": {"$text": "CA"}, "frequency": {"$text": "88.1"}, "orgId": {"$text": "1390"}, "image": [{"$text": "http://media.npr.org/images/stations/logos/kmue_fm.gif", "type": "logo"}], "marketCity": {"$text": "Eureka"}, "callLetters": {"$text": "KMUE"}, "coverage_url": {"$text": "/stations/station_xml/kmue-fm_88.1.xml"}, "guid": {"$text": "5228cf4c1d6348fa87af9c4b888db854"}, "id": "1390"}, {"orgDisplayName": {"$text": "Jefferson Public Radio"}, "group": {"$text": "Jefferson Public Radio", "id": "173"}, "name": {"$text": "KNHT-FM"}, "url": [{"typeId": "1", "$text": "http://www.ijpr.org/", "type": "Organization Home Page", "title": "Jefferson Public Radio Homepage"}, {"typeId": "2", "$text": "http://www.ijpr.org/ProgramGuide.asp?StationID=1", "type": "Program Schedule", "title": "Program Schedule"}, {"typeId": "4", "$text": "http://www.givetojpr.org", "type": "Pledge Page", "title": "Support JPR"}, {"typeId": "7", "$text": "http://www.ijpr.org/SectionIndex.asp?SectionID=1013", "type": "Audio Stream Landing Page", "title": "JPR Classics and News"}, {"typeId": "10", "title": "JPR Classics & News", "$text": "http://jpr.streamguys.org/jpr-classics.m3u", "primary": "true", "guid": "4fcf71380d8a43d2b44151cff2b09117", "type": "Audio MP3 Stream"}, {"typeId": "16", "$text": "http://www.facebook.com/JeffersonPublicRadio", "type": "Facebook Url", "title": "Facebook"}], "tagline": [{"$text": "Classics & News Service of Jefferson Public Radio"}], "signal": {"strength": "3", "$text": "moderate"}, "memberStatus": {"$text": "Member"}, "band": {"$text": "FM"}, "state": {"$text": "CA"}, "frequency": {"$text": "107.3"}, "orgId": {"$text": "185"}, "image": [{"$text": "http://media.npr.org/images/stations/logos/knht_fm.gif", "type": "logo"}], "marketCity": {"$text": "Rio Dell"}, "callLetters": {"$text": "KNHT"}, "coverage_url": {"$text": "/stations/station_xml/knht-fm_107.3.xml"}, "guid": {"$text": "4fcf700f0c894ba4a21b0c01a0e42f1f"}, "id": "185", "network": {"$text": "Jefferson Public Radio", "orgId": "172"}}, {"orgDisplayName": {"$text": "Jefferson Public Radio"}, "group": {"$text": "Jefferson Public Radio", "id": "173"}, "name": {"$text": "KNHM-FM"}, "url": [{"typeId": "1", "$text": "www.ijpr.org", "type": "Organization Home Page", "title": "KNHM-FM Homepage"}, {"typeId": "2", "$text": "http://ijpr.org/ProgramGuide.asp?StationID=3", "type": "Program Schedule", "title": "Program Schedule"}, {"typeId": "4", "$text": "http://www.givetojpr.org", "type": "Pledge Page", "title": "Support JPR"}, {"typeId": "7", "$text": "http://ijpr.org/SectionIndex.asp?SectionID=1013", "type": "Audio Stream Landing Page", "title": "JPR News and Information"}, {"typeId": "10", "title": "JPR News & Information", "$text": "http://jpr.streamguys.org/jpr-news.m3u", "primary": "true", "guid": "4fcf71381cbf41c7b0312cc8517117f0", "type": "Audio MP3 Stream"}], "tagline": [{"$text": "News & Information Service of Jefferson Public Radio"}], "signal": {"strength": "3", "$text": "moderate"}, "memberStatus": {"$text": "Non-Member - GF"}, "band": {"$text": "FM"}, "state": {"$text": "CA"}, "frequency": {"$text": "91.5"}, "orgId": {"$text": "1050"}, "image": [{"$text": "http://media.npr.org/images/stations/logos/knhm_fm.gif", "type": "logo"}], "marketCity": {"$text": "Bayside"}, "callLetters": {"$text": "KNHM"}, "coverage_url": {"$text": "/stations/station_xml/knhm-fm_91.5.xml"}, "guid": {"$text": "4fcf70140fc84ff58b5a2d74a36d954d"}, "id": "1050", "network": {"$text": "Jefferson Public Radio", "orgId": "172"}}, {"orgDisplayName": {"$text": "Oregon Public Broadcasting"}, "group": {"$text": "Oregon Public Broadcasting", "id": "135"}, "name": {"$text": "KOAC-AM"}, "url": [{"typeId": "1", "$text": "http://www.opb.org", "type": "Organization Home Page", "title": "OPB Home"}, {"typeId": "2", "$text": "http://www.opb.org/radio/?mode=schedule", "type": "Program Schedule", "title": "Radio Schedule"}, {"typeId": "4", "$text": "https://secure.opb.org/support/contribute/", "type": "Pledge Page", "title": "Support OPB"}, {"typeId": "7", "$text": "http://www.opb.org/programs/streams/", "type": "Audio Stream Landing Page", "title": "OPB - FM Stream"}, {"typeId": "8", "$text": "http://www.opb.org/thinkoutloud/feeds/shows/", "type": "RSS Feed", "title": "Think Out Loud"}, {"typeId": "10", "title": "opbmusic", "$text": "http://opbmusic.org/media/opbmusic.pls", "primary": "false", "guid": "4fcf71441d2048778f6f9d9004fc3496", "type": "Audio MP3 Stream"}, {"typeId": "10", "title": "Oregon Public Broadcasting", "$text": "http://stream5.opb.org/radio_player.mp3.m3u", "primary": "true", "guid": "4fcf714411d449d9975fb2c35f1bf61c", "type": "Audio MP3 Stream"}, {"typeId": "16", "$text": "http://www.facebook.com/oregonpublicbroadcasting", "type": "Facebook Url", "title": "Facebook"}], "tagline": [{"$text": "News. Arts. Life."}], "signal": {"strength": "1", "$text": "weak"}, "memberStatus": {"$text": "Member"}, "band": {"$text": "AM"}, "state": {"$text": "OR"}, "frequency": {"$text": "550"}, "orgId": {"$text": "132"}, "image": [{"$text": "http://media.npr.org/images/stations/logos/koac_am.gif", "type": "logo"}], "marketCity": {"$text": "Corvallis"}, "callLetters": {"$text": "KOAC"}, "coverage_url": {"$text": "/stations/station_xml/koac-am_550.xml"}, "guid": {"$text": "4fcf700e24714d03a589d45faa07b67c"}, "id": "132", "network": {"$text": "Oregon Public Broadcasting", "orgId": "134"}}, {"orgDisplayName": {"$text": "Jefferson Public Radio"}, "group": {"$text": "Jefferson Public Radio", "id": "173"}, "name": {"$text": "KAGI-AM"}, "url": [{"typeId": "1", "$text": "http://www.ijpr.org/", "type": "Organization Home Page", "title": "Jefferson Public Radio Homepage"}, {"typeId": "2", "$text": "http://www.ijpr.org/ProgramGuide.asp?StationID=3", "type": "Program Schedule", "title": "Program Schedule"}, {"typeId": "4", "$text": "http://www.givetojpr.org", "type": "Pledge Page", "title": "Support JPR"}, {"typeId": "7", "$text": "http://www.ijpr.org/Index.asp", "type": "Audio Stream Landing Page", "title": "JPR News"}, {"typeId": "10", "title": "JPR News & Information", "$text": "http://jpr.streamguys.org/jpr-news.m3u", "primary": "true", "guid": "4fcf71381cbf41c7b0312cc8517117f0", "type": "Audio MP3 Stream"}, {"typeId": "16", "$text": "http://www.facebook.com/JeffersonPublicRadio", "type": "Facebook Url", "title": "Facebook"}], "tagline": [{"$text": "News & Information Service of Jefferson Public Radio"}], "signal": {"strength": "1", "$text": "weak"}, "memberStatus": {"$text": "Member"}, "band": {"$text": "AM"}, "state": {"$text": "OR"}, "frequency": {"$text": "930"}, "orgId": {"$text": "174"}, "image": [{"$text": "http://media.npr.org/images/stations/logos/kagi_am.gif", "type": "logo"}], "marketCity": {"$text": "Ashland"}, "callLetters": {"$text": "KAGI"}, "coverage_url": {"$text": "/stations/station_xml/kagi-am_930.xml"}, "guid": {"$text": "4fcf700f098f458db150e502db8169b4"}, "id": "174", "network": {"$text": "Jefferson Public Radio", "orgId": "172"}}, {"orgDisplayName": {"$text": "Jefferson Public Radio"}, "group": {"$text": "Jefferson Public Radio", "id": "173"}, "name": {"$text": "KPMO-AM"}, "url": [{"typeId": "1", "$text": "http://www.ijpr.org/", "type": "Organization Home Page", "title": "KPMO-AM Homepage"}, {"typeId": "2", "$text": "http://ijpr.org/ProgramGuide.asp?StationID=3", "type": "Program Schedule", "title": "Program Schedule"}, {"typeId": "4", "$text": "http://www.givetojpr.org", "type": "Pledge Page", "title": "Support JPR"}, {"typeId": "7", "$text": "http://ijpr.org/SectionIndex.asp?SectionID=1013", "type": "Audio Stream Landing Page", "title": "JPR News and Information"}, {"typeId": "10", "title": "JPR News & Information", "$text": "http://jpr.streamguys.org/jpr-news.m3u", "primary": "true", "guid": "4fcf71381cbf41c7b0312cc8517117f0", "type": "Audio MP3 Stream"}], "tagline": [{"$text": "News & Information Service of Jefferson Public Radio"}], "signal": {"strength": "1", "$text": "weak"}, "memberStatus": {"$text": "Non-Member - GF"}, "band": {"$text": "AM"}, "state": {"$text": "CA"}, "frequency": {"$text": "1300"}, "orgId": {"$text": "928"}, "image": [{"$text": "http://media.npr.org/images/stations/logos/kpmo_am.gif", "type": "logo"}], "marketCity": {"$text": "Mendocino"}, "callLetters": {"$text": "KPMO"}, "coverage_url": {"$text": "/stations/station_xml/kpmo-am_1300.xml"}, "guid": {"$text": "4fcf70131e8941579c5d46ff3c2fefd8"}, "id": "928", "network": {"$text": "Jefferson Public Radio", "orgId": "172"}}, {"orgDisplayName": {}, "name": {"$text": "KMUD-FM"}, "tagline": [{}], "signal": {"strength": "1", "$text": "weak"}, "memberStatus": {"$text": "Non-Member"}, "band": {"$text": "FM"}, "state": {"$text": "CA"}, "frequency": {"$text": "91.1"}, "orgId": {"$text": "1257"}, "image": [{"$text": "http://media.npr.org/images/stations/logos/kmud_fm.gif", "type": "logo"}], "marketCity": {"$text": "Garberville"}, "callLetters": {"$text": "KMUD"}, "coverage_url": {"$text": "/stations/station_xml/kmud-fm_91.1.xml"}, "guid": {"$text": "4fcf701508ba4ad4b1a46aeff793bd56"}, "id": "1257"}, {"translator_band": {"$text": "FX"}, "name": {"$text": "KHSU-FM"}, "tagline": [{"$text": "Diverse Public Radio"}], "signal": {"strength": "1", "$text": "weak"}, "memberStatus": {"$text": "Translator"}, "state": {"$text": "CA"}, "band": {"$text": "FM"}, "translator_callLetters": {"$text": "K259AL"}, "frequency": {"$text": "99.9"}, "orgId": {"$text": "5131158"}, "image": [{"$text": "http://media.npr.org/images/stations/logos/khsu_fm.gif", "type": "logo"}], "marketCity": {"$text": "Arcata"}, "callLetters": {"$text": "KHSU"}, "coverage_url": {"$text": "/stations/station_xml/khsu-fm_99.9.k259al-fx.xml"}, "guid": {"$text": "503ceb59103a43c495fdd2c31fe8ebe2"}, "orgDisplayName": {"$text": "KHSU"}, "id": "5131158", "network": {"$text": "KHSU-FM", "orgId": "92"}}], "version": "0.94", "title": {"$text": "Stations near 95521"}}